djangorestframework_files-1.0.1.dist-info/DESCRIPTION.rst
djangorestframework_files-1.0.1.dist-info/METADATA
djangorestframework_files-1.0.1.dist-info/RECORD
djangorestframework_files-1.0.1.dist-info/WHEEL
djangorestframework_files-1.0.1.dist-info/metadata.json
djangorestframework_files-1.0.1.dist-info/top_level.txt
rest_framework_files/__init__.py
rest_framework_files/generics.py
rest_framework_files/mixins.py
rest_framework_files/routers.py
rest_framework_files/viewsets.py
